{"openapi": "3.1.0", "info": {"title": "Landsat Web Tracker API", "version": "0.1.0"}, "paths": {"/healthcheck": {"get": {"summary": "Healthcheck", "operationId": "healthcheck_healthcheck_get", "responses": {"200": {"description": "Successful Response", "content": {"application/json": {"schema": {}}}}}}}, "/": {"get": {"summary": "Read Main", "operationId": "read_main__get", "responses": {"200": {"description": "Successful Response", "content": {"application/json": {"schema": {}}}}}}}, "/coordinates/lookup": {"get": {"summary": "Coordinates Lookup", "operationId": "coordinates_lookup_coordinates_lookup_get", "responses": {"200": {"description": "Successful Response", "content": {"application/json": {"schema": {}}}}}}}, "/coordinates/scene-detection": {"get": {"summary": "Scene Detection", "operationId": "scene_detection_coordinates_scene_detection_get", "responses": {"200": {"description": "Successful Response", "content": {"application/json": {"schema": {}}}}}}}, "/landsat/search": {"get": {"summary": "Search", "operationId": "search_landsat_search_get", "parameters": [{"name": "latitude", "in": "query", "required": true, "schema": {"type": "number", "title": "Latitude"}}, {"name": "longitude", "in": "query", "required": true, "schema": {"type": "number", "title": "Longitude"}}, {"name": "start_date", "in": "query", "required": true, "schema": {"type": "string", "format": "date-time", "title": "Start Date"}}, {"name": "end_date", "in": "query", "required": true, "schema": {"type": "string", "format": "date-time", "title": "End Date"}}, {"name": "max_cloud_cover", "in": "query", "required": false, "schema": {"type": "number", "default": 0.2, "title": "Max Cloud Cover"}}, {"name": "max_items", "in": "query", "required": false, "schema": {"type": "integer", "default": 5, "title": "Max Items"}}, {"name": "limit", "in": "query", "required": false, "schema": {"type": "integer", "default": 5, "title": "Limit"}}], "responses": {"200": {"description": "Successful Response", "content": {"application/json": {"schema": {"type": "array", "items": {"$ref": "#/components/schemas/LandsatItem"}, "title": "Response Search Landsat Search Get"}}}}, "422": {"description": "Validation Error", "content": {"application/json": {"schema": {"$ref": "#/components/schemas/HTTPValidationError"}}}}}}}, "/auth/get_user": {"get": {"summary": "Get User", "description": "Returns Supabase user information", "operationId": "get_user_auth_get_user_get", "responses": {"200": {"description": "Successful Response", "content": {"application/json": {"schema": {}}}}}, "security": [{"OAuth2PasswordBearer": []}]}}}, "components": {"schemas": {"Coordinates": {"properties": {"lat": {"type": "number", "maximum": 90.0, "minimum": -90.0, "title": "Lat"}, "lon": {"type": "number", "maximum": 180.0, "minimum": -180.0, "title": "Lon"}}, "type": "object", "required": ["lat", "lon"], "title": "Coordinates"}, "HTTPValidationError": {"properties": {"detail": {"items": {"$ref": "#/components/schemas/ValidationError"}, "type": "array", "title": "Detail"}}, "type": "object", "title": "HTTPValidationError"}, "LandsatItem": {"properties": {"id": {"type": "string", "title": "Id"}, "scene_id": {"type": "string", "title": "Scene Id"}, "datetime": {"type": "string", "format": "date-time", "title": "Datetime"}, "eo_cloud_cover": {"type": "number", "title": "Eo Cloud Cover"}, "wrs_coordinates": {"$ref": "#/components/schemas/WrsCoordinates"}, "rendered_preview": {"type": "string", "title": "Rendered Preview"}, "polygon": {"$ref": "#/components/schemas/Polygon"}}, "type": "object", "required": ["id", "scene_id", "datetime", "eo_cloud_cover", "wrs_coordinates", "rendered_preview", "polygon"], "title": "LandsatItem"}, "Polygon": {"properties": {"coordinates": {"items": {"$ref": "#/components/schemas/Coordinates"}, "type": "array", "title": "Coordinates"}}, "type": "object", "required": ["coordinates"], "title": "Polygon"}, "ValidationError": {"properties": {"loc": {"items": {"anyOf": [{"type": "string"}, {"type": "integer"}]}, "type": "array", "title": "Location"}, "msg": {"type": "string", "title": "Message"}, "type": {"type": "string", "title": "Error Type"}}, "type": "object", "required": ["loc", "msg", "type"], "title": "ValidationError"}, "WrsCoordinates": {"properties": {"path": {"type": "integer", "maximum": 233.0, "minimum": 1.0, "title": "Path"}, "row": {"type": "integer", "maximum": 248.0, "minimum": 1.0, "title": "Row"}}, "type": "object", "required": ["path", "row"], "title": "WrsCoordinates"}}, "securitySchemes": {"OAuth2PasswordBearer": {"type": "oauth2", "flows": {"password": {"scopes": {}, "tokenUrl": "token"}}}}}}